{
  "header": "",
  "footer": "",
  "language": "Greek",
  "verses": [
    {
      "book_id": "1CO",
      "book_name": "1 Corinthians",
      "chapter": 8,
      "verse_start": 1,
      "verse_end": 1,
      "text": [
        "περι",
        "δε",
        "των",
        "ειδωλοθυτων",
        "οιδαμεν",
        "οτι",
        "παντες",
        "γνωσιν",
        "εχομεν",
        "η",
        "γνωσις",
        "φυσιοι",
        "η",
        "δε",
        "αγαπη",
        "οικοδομει"
      ],
      "info": ""
    },
    {
      "book_id": "1CO",
      "book_name": "1 Corinthians",
      "chapter": 8,
      "verse_start": 2,
      "verse_end": 2,
      "text": [
        "ει",
        "δε",
        "τις",
        "δοκει",
        "ειδεναι",
        "τι",
        "ουδεπω",
        "ουδεν",
        "εγνωκεν",
        "καθως",
        "δει",
        "γνωναι"
      ],
      "info": ""
    },
    {
      "book_id": "1CO",
      "book_name": "1 Corinthians",
      "chapter": 8,
      "verse_start": 3,
      "verse_end": 3,
      "text": [
        "ει",
        "δε",
        "τις",
        "αγαπα",
        "τον",
        "θεον",
        "ουτος",
        "εγνωσται",
        "υπ",
        "αυτου"
      ],
      "info": ""
    },
    {
      "book_id": "1CO",
      "book_name": "1 Corinthians",
      "chapter": 8,
      "verse_start": 4,
      "verse_end": 4,
      "text": [
        "περι",
        "της",
        "βρωσεως",
        "ουν",
        "των",
        "ειδωλοθυτων",
        "οιδαμεν",
        "οτι",
        "ουδεν",
        "ειδωλον",
        "εν",
        "κοσμω",
        "και",
        "οτι",
        "ουδεις",
        "θεος",
        "ετερος",
        "ει",
        "μη",
        "εις"
      ],
      "info": ""
    },
    {
      "book_id": "1CO",
      "book_name": "1 Corinthians",
      "chapter": 8,
      "verse_start": 5,
      "verse_end": 5,
      "text": [
        "και",
        "γαρ",
        "ειπερ",
        "εισιν",
        "λεγομενοι",
        "θεοι",
        "ειτε",
        "εν",
        "ουρανω",
        "ειτε",
        "επι",
        "της",
        "γης",
        "ωσπερ",
        "εισιν",
        "θεοι",
        "πολλοι",
        "και",
        "κυριοι",
        "πολλοι"
      ],
      "info": ""
    },
    {
      "book_id": "1CO",
      "book_name": "1 Corinthians",
      "chapter": 8,
      "verse_start": 6,
      "verse_end": 6,
      "text": [
        "αλλ",
        "ημιν",
        "εις",
        "θεος",
        "ο",
        "πατηρ",
        "εξ",
        "ου",
        "τα",
        "παντα",
        "και",
        "ημεις",
        "εις",
        "αυτον",
        "και",
        "εις",
        "κυριος",
        "ιησους",
        "χριστος",
        "δι",
        "ου",
        "τα",
        "παντα",
        "και",
        "ημεις",
        "δι",
        "αυτου"
      ],
      "info": ""
    },
    {
      "book_id": "1CO",
      "book_name": "1 Corinthians",
      "chapter": 8,
      "verse_start": 7,
      "verse_end": 7,
      "text": [
        "αλλ",
        "ουκ",
        "εν",
        "πασιν",
        "η",
        "γνωσις",
        "τινες",
        "δε",
        "τη",
        "συνειδησει",
        "του",
        "ειδωλου",
        "εως",
        "αρτι",
        "ως",
        "ειδωλοθυτον",
        "εσθιουσιν",
        "και",
        "η",
        "συνειδησις",
        "αυτων",
        "ασθενης",
        "ουσα",
        "μολυνεται"
      ],
      "info": ""
    },
    {
      "book_id": "1CO",
      "book_name": "1 Corinthians",
      "chapter": 8,
      "verse_start": 8,
      "verse_end": 8,
      "text": [
        "βρωμα",
        "δε",
        "ημας",
        "ου",
        "παριστησιν",
        "τω",
        "θεω",
        "ουτε",
        "γαρ",
        "εαν",
        "φαγωμεν",
        "περισσευομεν",
        "ουτε",
        "εαν",
        "μη",
        "φαγωμεν",
        "υστερουμεθα"
      ],
      "info": ""
    },
    {
      "book_id": "1CO",
      "book_name": "1 Corinthians",
      "chapter": 8,
      "verse_start": 9,
      "verse_end": 9,
      "text": [
        "βλεπετε",
        "δε",
        "μηπως",
        "η",
        "εξουσια",
        "υμων",
        "αυτη",
        "προσκομμα",
        "γενηται",
        "τοις",
        "ασθενουσιν"
      ],
      "info": ""
    },
    {
      "book_id": "1CO",
      "book_name": "1 Corinthians",
      "chapter": 8,
      "verse_start": 10,
      "verse_end": 10,
      "text": [
        "εαν",
        "γαρ",
        "τις",
        "ιδη",
        "σε",
        "τον",
        "εχοντα",
        "γνωσιν",
        "εν",
        "ειδωλειω",
        "κατακειμενον",
        "ουχι",
        "η",
        "συνειδησις",
        "αυτου",
        "ασθενους",
        "οντος",
        "οικοδομηθησεται",
        "εις",
        "το",
        "τα",
        "ειδωλοθυτα",
        "εσθιειν"
      ],
      "info": ""
    },
    {
      "book_id": "1CO",
      "book_name": "1 Corinthians",
      "chapter": 8,
      "verse_start": 11,
      "verse_end": 11,
      "text": [
        "και",
        "απολειται",
        "ο",
        "ασθενων",
        "αδελφος",
        "επι",
        "τη",
        "ση",
        "γνωσει",
        "δι",
        "ον",
        "χριστος",
        "απεθανεν"
      ],
      "info": ""
    },
    {
      "book_id": "1CO",
      "book_name": "1 Corinthians",
      "chapter": 8,
      "verse_start": 12,
      "verse_end": 12,
      "text": [
        "ουτως",
        "δε",
        "αμαρτανοντες",
        "εις",
        "τους",
        "αδελφους",
        "και",
        "τυπτοντες",
        "αυτων",
        "την",
        "συνειδησιν",
        "ασθενουσαν",
        "εις",
        "χριστον",
        "αμαρτανετε"
      ],
      "info": ""
    },
    {
      "book_id": "1CO",
      "book_name": "1 Corinthians",
      "chapter": 8,
      "verse_start": 13,
      "verse_end": 13,
      "text": [
        "διοπερ",
        "ει",
        "βρωμα",
        "σκανδαλιζει",
        "τον",
        "αδελφον",
        "μου",
        "ου",
        "μη",
        "φαγω",
        "κρεα",
        "εις",
        "τον",
        "αιωνα",
        "ινα",
        "μη",
        "τον",
        "αδελφον",
        "μου",
        "σκανδαλισω"
      ],
      "info": ""
    }
  ]
}