{
  "header": "",
  "footer": "",
  "language": "English",
  "verses": [
    {
      "book_id": "2KI",
      "book_name": "2 Kings",
      "chapter": 4,
      "verse_start": 1,
      "verse_end": 1,
      "text": [
        "Now",
        "there",
        "cryed",
        "a",
        "certaine",
        "woman",
        "of",
        "the",
        "wiues",
        "of",
        "the",
        "sonnes",
        "of",
        "the",
        "Prophets",
        "vnto",
        "Elisha,",
        "saying,",
        "Thy",
        "seruant",
        "my",
        "husband",
        "is",
        "dead,",
        "and",
        "thou",
        "knowest",
        "that",
        "thy",
        "seruant",
        "did",
        "feare",
        "the",
        "Lord:",
        "and",
        "the",
        "creditour",
        "is",
        "come",
        "to",
        "take",
        "vnto",
        "him",
        "my",
        "two",
        "sonnes",
        "to",
        "be",
        "bondmen."
      ],
      "info": ""
    },
    {
      "book_id": "2KI",
      "book_name": "2 Kings",
      "chapter": 4,
      "verse_start": 2,
      "verse_end": 2,
      "text": [
        "And",
        "Elisha",
        "said",
        "vnto",
        "her,",
        "What",
        "shall",
        "I",
        "doe",
        "for",
        "thee?",
        "Tell",
        "mee,",
        "what",
        "hast",
        "thou",
        "in",
        "the",
        "house?",
        "And",
        "shee",
        "sayd,",
        "Thine",
        "handmaid",
        "hath",
        "not",
        "any",
        "thing",
        "in",
        "the",
        "house,",
        "saue",
        "a",
        "pot",
        "of",
        "oyle."
      ],
      "info": ""
    },
    {
      "book_id": "2KI",
      "book_name": "2 Kings",
      "chapter": 4,
      "verse_start": 3,
      "verse_end": 3,
      "text": [
        "Then",
        "hee",
        "said,",
        "Goe,",
        "borrow",
        "thee",
        "vessels",
        "abroad,",
        "of",
        "all",
        "thy",
        "neighbours;",
        "euen",
        "emptie",
        "vessels,",
        "borrow",
        "not",
        "a",
        "few."
      ],
      "info": ""
    },
    {
      "book_id": "2KI",
      "book_name": "2 Kings",
      "chapter": 4,
      "verse_start": 4,
      "verse_end": 4,
      "text": [
        "And",
        "when",
        "thou",
        "art",
        "come",
        "in,",
        "thou",
        "shalt",
        "shut",
        "the",
        "doore",
        "vpon",
        "thee,",
        "and",
        "vpon",
        "thy",
        "sonnes,",
        "and",
        "shalt",
        "powre",
        "out",
        "into",
        "all",
        "those",
        "vessels,",
        "and",
        "thou",
        "shalt",
        "set",
        "aside",
        "that",
        "which",
        "is",
        "full."
      ],
      "info": ""
    },
    {
      "book_id": "2KI",
      "book_name": "2 Kings",
      "chapter": 4,
      "verse_start": 5,
      "verse_end": 5,
      "text": [
        "So",
        "shee",
        "went",
        "from",
        "him,",
        "and",
        "shut",
        "the",
        "doore",
        "vpon",
        "her,",
        "&amp;",
        "vpon",
        "her",
        "sonnes:",
        "who",
        "brought",
        "the",
        "vessels",
        "to",
        "her,",
        "and",
        "shee",
        "powred",
        "out."
      ],
      "info": ""
    },
    {
      "book_id": "2KI",
      "book_name": "2 Kings",
      "chapter": 4,
      "verse_start": 6,
      "verse_end": 6,
      "text": [
        "And",
        "it",
        "came",
        "to",
        "passe,",
        "when",
        "the",
        "vessels",
        "were",
        "full,",
        "that",
        "shee",
        "said",
        "vnto",
        "her",
        "sonne,",
        "Bring",
        "me",
        "yet",
        "a",
        "vessell.",
        "And",
        "hee",
        "said",
        "vnto",
        "her,",
        "There",
        "is",
        "not",
        "a",
        "vessel",
        "more.",
        "And",
        "the",
        "oyle",
        "stayed."
      ],
      "info": ""
    },
    {
      "book_id": "2KI",
      "book_name": "2 Kings",
      "chapter": 4,
      "verse_start": 7,
      "verse_end": 7,
      "text": [
        "Then",
        "she",
        "came,",
        "and",
        "told",
        "the",
        "man",
        "of",
        "God:",
        "and",
        "he",
        "said,",
        "Goe,",
        "sell",
        "the",
        "oyle,",
        "and",
        "pay",
        "thy",
        "debt,",
        "and",
        "liue",
        "thou",
        "and",
        "thy",
        "children",
        "of",
        "the",
        "rest."
      ],
      "info": ""
    },
    {
      "book_id": "2KI",
      "book_name": "2 Kings",
      "chapter": 4,
      "verse_start": 8,
      "verse_end": 8,
      "text": [
        "¶",
        "And",
        "it",
        "fell",
        "on",
        "a",
        "day,",
        "that",
        "Elisha",
        "passed",
        "to",
        "Shunem,",
        "where",
        "was",
        "a",
        "great",
        "woman;",
        "and",
        "shee",
        "constrained",
        "him",
        "to",
        "eate",
        "bread:",
        "And",
        "so",
        "it",
        "was,",
        "that",
        "as",
        "oft",
        "as",
        "he",
        "passed",
        "by,",
        "hee",
        "turned",
        "in",
        "thither",
        "to",
        "eate",
        "bread."
      ],
      "info": ""
    },
    {
      "book_id": "2KI",
      "book_name": "2 Kings",
      "chapter": 4,
      "verse_start": 9,
      "verse_end": 9,
      "text": [
        "And",
        "shee",
        "said",
        "vnto",
        "her",
        "husband,",
        "Behold",
        "now,",
        "I",
        "perceiue",
        "that",
        "this",
        "is",
        "an",
        "holy",
        "man",
        "of",
        "God,",
        "which",
        "passeth",
        "by",
        "vs",
        "continually."
      ],
      "info": ""
    },
    {
      "book_id": "2KI",
      "book_name": "2 Kings",
      "chapter": 4,
      "verse_start": 10,
      "verse_end": 10,
      "text": [
        "Let",
        "vs",
        "make",
        "a",
        "litle",
        "chamber,",
        "I",
        "pray",
        "thee,",
        "on",
        "the",
        "wall,",
        "and",
        "let",
        "vs",
        "set",
        "for",
        "him",
        "there",
        "a",
        "bed,",
        "and",
        "a",
        "table,",
        "and",
        "a",
        "stoole,",
        "and",
        "a",
        "candlesticke:",
        "and",
        "it",
        "shall",
        "be",
        "when",
        "he",
        "commeth",
        "to",
        "vs,",
        "that",
        "hee",
        "shall",
        "turne",
        "in",
        "thither."
      ],
      "info": ""
    },
    {
      "book_id": "2KI",
      "book_name": "2 Kings",
      "chapter": 4,
      "verse_start": 11,
      "verse_end": 11,
      "text": [
        "And",
        "it",
        "fell",
        "on",
        "a",
        "day",
        "that",
        "hee",
        "came",
        "thither,",
        "and",
        "hee",
        "turned",
        "into",
        "the",
        "chamber,",
        "and",
        "lay",
        "there."
      ],
      "info": ""
    },
    {
      "book_id": "2KI",
      "book_name": "2 Kings",
      "chapter": 4,
      "verse_start": 12,
      "verse_end": 12,
      "text": [
        "And",
        "he",
        "said",
        "to",
        "Gehazi",
        "his",
        "seruant,",
        "Call",
        "this",
        "Shunammite.",
        "And",
        "when",
        "hee",
        "had",
        "called",
        "her,",
        "she",
        "stood",
        "before",
        "him."
      ],
      "info": ""
    },
    {
      "book_id": "2KI",
      "book_name": "2 Kings",
      "chapter": 4,
      "verse_start": 13,
      "verse_end": 13,
      "text": [
        "And",
        "he",
        "said",
        "vnto",
        "him,",
        "Say,",
        "now",
        "vnto",
        "her,",
        "Behold,",
        "thou",
        "hast",
        "beene",
        "carefull",
        "for",
        "vs",
        "with",
        "all",
        "this",
        "care;",
        "What",
        "is",
        "to",
        "be",
        "done",
        "for",
        "thee?",
        "Wouldest",
        "thou",
        "be",
        "spoken",
        "for",
        "to",
        "the",
        "king,",
        "or",
        "to",
        "the",
        "captaine",
        "of",
        "the",
        "hoste?",
        "And",
        "she",
        "answered,",
        "I",
        "dwell",
        "among",
        "mine",
        "owne",
        "people."
      ],
      "info": ""
    },
    {
      "book_id": "2KI",
      "book_name": "2 Kings",
      "chapter": 4,
      "verse_start": 14,
      "verse_end": 14,
      "text": [
        "And",
        "he",
        "said,",
        "What",
        "then",
        "is",
        "to",
        "bee",
        "done",
        "for",
        "her?",
        "And",
        "Gehazi",
        "answered,",
        "Uerily",
        "she",
        "hath",
        "no",
        "child,",
        "and",
        "her",
        "husband",
        "is",
        "old."
      ],
      "info": ""
    },
    {
      "book_id": "2KI",
      "book_name": "2 Kings",
      "chapter": 4,
      "verse_start": 15,
      "verse_end": 15,
      "text": [
        "And",
        "he",
        "said,",
        "Call",
        "her.",
        "And",
        "when",
        "he",
        "had",
        "called",
        "her,",
        "she",
        "stood",
        "in",
        "the",
        "doore."
      ],
      "info": ""
    },
    {
      "book_id": "2KI",
      "book_name": "2 Kings",
      "chapter": 4,
      "verse_start": 16,
      "verse_end": 16,
      "text": [
        "And",
        "he",
        "said,",
        "About",
        "this",
        "season,",
        "according",
        "to",
        "the",
        "time",
        "of",
        "life,",
        "thou",
        "shalt",
        "imbrace",
        "a",
        "sonne.",
        "And",
        "she",
        "said,",
        "Nay",
        "my",
        "lord,",
        "thou",
        "man",
        "of",
        "God,",
        "doe",
        "not",
        "lie",
        "vnto",
        "thine",
        "handmaid."
      ],
      "info": ""
    },
    {
      "book_id": "2KI",
      "book_name": "2 Kings",
      "chapter": 4,
      "verse_start": 17,
      "verse_end": 17,
      "text": [
        "And",
        "the",
        "woman",
        "conceiued,",
        "and",
        "bare",
        "a",
        "sonne",
        "at",
        "that",
        "season,",
        "that",
        "Elisha",
        "had",
        "said",
        "vnto",
        "her,",
        "according",
        "to",
        "the",
        "time",
        "of",
        "life."
      ],
      "info": ""
    },
    {
      "book_id": "2KI",
      "book_name": "2 Kings",
      "chapter": 4,
      "verse_start": 18,
      "verse_end": 18,
      "text": [
        "¶",
        "And",
        "when",
        "the",
        "child",
        "was",
        "growen,",
        "it",
        "fell",
        "on",
        "a",
        "day",
        "that",
        "hee",
        "went",
        "out",
        "to",
        "his",
        "father,",
        "to",
        "the",
        "reapers."
      ],
      "info": ""
    },
    {
      "book_id": "2KI",
      "book_name": "2 Kings",
      "chapter": 4,
      "verse_start": 19,
      "verse_end": 19,
      "text": [
        "And",
        "he",
        "said",
        "vnto",
        "his",
        "father,",
        "My",
        "head,",
        "my",
        "head:",
        "and",
        "he",
        "said",
        "to",
        "a",
        "ladde,",
        "Carie",
        "him",
        "to",
        "his",
        "mother."
      ],
      "info": ""
    },
    {
      "book_id": "2KI",
      "book_name": "2 Kings",
      "chapter": 4,
      "verse_start": 20,
      "verse_end": 20,
      "text": [
        "And",
        "when",
        "he",
        "had",
        "taken",
        "him,",
        "and",
        "brought",
        "him",
        "to",
        "his",
        "mother,",
        "hee",
        "sate",
        "on",
        "her",
        "knees",
        "till",
        "noone,",
        "and",
        "then",
        "died."
      ],
      "info": ""
    },
    {
      "book_id": "2KI",
      "book_name": "2 Kings",
      "chapter": 4,
      "verse_start": 21,
      "verse_end": 21,
      "text": [
        "And",
        "she",
        "went",
        "vp,",
        "and",
        "laid",
        "him",
        "on",
        "the",
        "bed",
        "of",
        "the",
        "man",
        "of",
        "God,",
        "and",
        "shut",
        "the",
        "doore",
        "vpon",
        "him,",
        "and",
        "went",
        "out."
      ],
      "info": ""
    },
    {
      "book_id": "2KI",
      "book_name": "2 Kings",
      "chapter": 4,
      "verse_start": 22,
      "verse_end": 22,
      "text": [
        "And",
        "she",
        "called",
        "vnto",
        "her",
        "husband,",
        "and",
        "said,",
        "Send",
        "me,",
        "I",
        "pray",
        "thee,",
        "one",
        "of",
        "the",
        "yong",
        "men,",
        "and",
        "one",
        "of",
        "the",
        "asses,",
        "that",
        "I",
        "may",
        "runne",
        "to",
        "the",
        "man",
        "of",
        "God,",
        "and",
        "come",
        "againe."
      ],
      "info": ""
    },
    {
      "book_id": "2KI",
      "book_name": "2 Kings",
      "chapter": 4,
      "verse_start": 23,
      "verse_end": 23,
      "text": [
        "And",
        "he",
        "said,",
        "Wherefore",
        "wilt",
        "thou",
        "goe",
        "to",
        "him",
        "to",
        "day?",
        "it",
        "is",
        "neither",
        "newe",
        "moone",
        "nor",
        "Sabbath.",
        "And",
        "shee",
        "said,",
        "It",
        "shalbe",
        "well."
      ],
      "info": ""
    },
    {
      "book_id": "2KI",
      "book_name": "2 Kings",
      "chapter": 4,
      "verse_start": 24,
      "verse_end": 24,
      "text": [
        "Then",
        "she",
        "sadled",
        "an",
        "asse,",
        "and",
        "said",
        "to",
        "her",
        "seruant,",
        "Driue,",
        "and",
        "goe",
        "forward:",
        "slacke",
        "not",
        "thy",
        "riding",
        "for",
        "mee,",
        "except",
        "I",
        "bid",
        "thee."
      ],
      "info": ""
    },
    {
      "book_id": "2KI",
      "book_name": "2 Kings",
      "chapter": 4,
      "verse_start": 25,
      "verse_end": 25,
      "text": [
        "So",
        "she",
        "went,",
        "and",
        "came",
        "vnto",
        "the",
        "man",
        "of",
        "God",
        "to",
        "mount",
        "Carmel:",
        "and",
        "it",
        "came",
        "to",
        "passe",
        "when",
        "the",
        "man",
        "of",
        "God",
        "saw",
        "her",
        "afarre",
        "off,",
        "that",
        "hee",
        "said",
        "to",
        "Gehazi",
        "his",
        "seruant,",
        "Behold,",
        "yonder",
        "is",
        "that",
        "Shunammite:"
      ],
      "info": ""
    },
    {
      "book_id": "2KI",
      "book_name": "2 Kings",
      "chapter": 4,
      "verse_start": 26,
      "verse_end": 26,
      "text": [
        "Runne",
        "now,",
        "I",
        "pray",
        "thee,",
        "to",
        "meet",
        "her,",
        "and",
        "say",
        "vnto",
        "her,",
        "Is",
        "it",
        "wel",
        "with",
        "thee?",
        "is",
        "it",
        "wel",
        "with",
        "thy",
        "husband?",
        "is",
        "it",
        "wel",
        "with",
        "the",
        "child?",
        "And",
        "she",
        "answered,",
        "It",
        "is",
        "well."
      ],
      "info": ""
    },
    {
      "book_id": "2KI",
      "book_name": "2 Kings",
      "chapter": 4,
      "verse_start": 27,
      "verse_end": 27,
      "text": [
        "And",
        "when",
        "shee",
        "came",
        "to",
        "the",
        "man",
        "of",
        "God",
        "to",
        "the",
        "hill,",
        "shee",
        "caught",
        "him",
        "by",
        "the",
        "feet:",
        "but",
        "Gehazi",
        "came",
        "neere",
        "to",
        "thrust",
        "her",
        "away.",
        "And",
        "the",
        "man",
        "of",
        "God",
        "saide,",
        "Let",
        "her",
        "alone,",
        "for",
        "her",
        "soule",
        "is",
        "vexed",
        "within",
        "her:",
        "and",
        "the",
        "Lord",
        "hath",
        "hid",
        "it",
        "from",
        "me,",
        "and",
        "hath",
        "not",
        "told",
        "me."
      ],
      "info": ""
    },
    {
      "book_id": "2KI",
      "book_name": "2 Kings",
      "chapter": 4,
      "verse_start": 28,
      "verse_end": 28,
      "text": [
        "Then",
        "shee",
        "said,",
        "Did",
        "I",
        "desire",
        "a",
        "sonne",
        "of",
        "my",
        "Lord",
        "?",
        "did",
        "I",
        "not",
        "say,",
        "Doe",
        "not",
        "deceiue",
        "me?"
      ],
      "info": ""
    },
    {
      "book_id": "2KI",
      "book_name": "2 Kings",
      "chapter": 4,
      "verse_start": 29,
      "verse_end": 29,
      "text": [
        "Then",
        "he",
        "said",
        "to",
        "Gehazi,",
        "Gird",
        "vp",
        "thy",
        "loines,",
        "and",
        "take",
        "my",
        "staffe",
        "in",
        "thine",
        "hand,",
        "and",
        "goe",
        "thy",
        "way:",
        "if",
        "thou",
        "meete",
        "any",
        "man,",
        "salute",
        "him",
        "not:",
        "and",
        "if",
        "any",
        "salute",
        "thee,",
        "answere",
        "him",
        "not",
        "againe:",
        "and",
        "lay",
        "my",
        "staffe",
        "vpon",
        "the",
        "face",
        "of",
        "the",
        "childe."
      ],
      "info": ""
    },
    {
      "book_id": "2KI",
      "book_name": "2 Kings",
      "chapter": 4,
      "verse_start": 30,
      "verse_end": 30,
      "text": [
        "And",
        "the",
        "mother",
        "of",
        "the",
        "childe",
        "said,",
        "As",
        "the",
        "Lord",
        "liueth,",
        "and",
        "as",
        "thy",
        "soule",
        "liueth,",
        "I",
        "will",
        "not",
        "leaue",
        "thee.",
        "And",
        "he",
        "arose,",
        "and",
        "followed",
        "her."
      ],
      "info": ""
    },
    {
      "book_id": "2KI",
      "book_name": "2 Kings",
      "chapter": 4,
      "verse_start": 31,
      "verse_end": 31,
      "text": [
        "And",
        "Gehazi",
        "passed",
        "on",
        "before",
        "them,",
        "and",
        "laid",
        "the",
        "staffe",
        "vpon",
        "the",
        "face",
        "of",
        "the",
        "child,",
        "but",
        "there",
        "was",
        "neither",
        "voyce,",
        "nor",
        "hearing:",
        "wherefore",
        "he",
        "went",
        "againe",
        "to",
        "meete",
        "him,",
        "and",
        "tolde",
        "him,",
        "saying,",
        "The",
        "child",
        "is",
        "not",
        "awaked."
      ],
      "info": ""
    },
    {
      "book_id": "2KI",
      "book_name": "2 Kings",
      "chapter": 4,
      "verse_start": 32,
      "verse_end": 32,
      "text": [
        "And",
        "when",
        "Elisha",
        "was",
        "come",
        "into",
        "the",
        "house,",
        "behold,",
        "the",
        "child",
        "was",
        "dead,",
        "and",
        "laid",
        "vpon",
        "his",
        "bed."
      ],
      "info": ""
    },
    {
      "book_id": "2KI",
      "book_name": "2 Kings",
      "chapter": 4,
      "verse_start": 33,
      "verse_end": 33,
      "text": [
        "He",
        "went",
        "in",
        "therefore,",
        "and",
        "shut",
        "the",
        "doore",
        "vpon",
        "them",
        "twaine,",
        "and",
        "prayed",
        "vnto",
        "the",
        "Lord."
      ],
      "info": ""
    },
    {
      "book_id": "2KI",
      "book_name": "2 Kings",
      "chapter": 4,
      "verse_start": 34,
      "verse_end": 34,
      "text": [
        "And",
        "he",
        "went",
        "vp,",
        "and",
        "lay",
        "vpon",
        "the",
        "child,",
        "and",
        "put",
        "his",
        "mouth",
        "vpon",
        "his",
        "mouth,",
        "and",
        "his",
        "eyes",
        "vpon",
        "his",
        "eyes,",
        "and",
        "his",
        "hands",
        "vpon",
        "his",
        "hands,",
        "and",
        "he",
        "stretched",
        "himselfe",
        "vpon",
        "the",
        "child,",
        "and",
        "the",
        "flesh",
        "of",
        "the",
        "child",
        "waxed",
        "warme."
      ],
      "info": ""
    },
    {
      "book_id": "2KI",
      "book_name": "2 Kings",
      "chapter": 4,
      "verse_start": 35,
      "verse_end": 35,
      "text": [
        "Then",
        "he",
        "returned,",
        "and",
        "walked",
        "in",
        "the",
        "house",
        "to",
        "and",
        "fro,",
        "and",
        "went",
        "vp,",
        "and",
        "stretched",
        "himselfe",
        "vpon",
        "him:",
        "and",
        "the",
        "child",
        "neesed",
        "seuen",
        "times,",
        "and",
        "the",
        "child",
        "opened",
        "his",
        "eyes."
      ],
      "info": ""
    },
    {
      "book_id": "2KI",
      "book_name": "2 Kings",
      "chapter": 4,
      "verse_start": 36,
      "verse_end": 36,
      "text": [
        "And",
        "hee",
        "called",
        "Gehazi,",
        "and",
        "said,",
        "Call",
        "this",
        "Shunammite.",
        "So",
        "hee",
        "called",
        "her:",
        "and",
        "when",
        "shee",
        "was",
        "come",
        "in",
        "vnto",
        "him,",
        "he",
        "said,",
        "Take",
        "vp",
        "thy",
        "sonne."
      ],
      "info": ""
    },
    {
      "book_id": "2KI",
      "book_name": "2 Kings",
      "chapter": 4,
      "verse_start": 37,
      "verse_end": 37,
      "text": [
        "Then",
        "she",
        "went",
        "in,",
        "and",
        "fell",
        "at",
        "his",
        "feet,",
        "and",
        "bowed",
        "her",
        "selfe",
        "to",
        "the",
        "ground,",
        "and",
        "tooke",
        "vp",
        "her",
        "sonne,",
        "and",
        "went",
        "out."
      ],
      "info": ""
    },
    {
      "book_id": "2KI",
      "book_name": "2 Kings",
      "chapter": 4,
      "verse_start": 38,
      "verse_end": 38,
      "text": [
        "¶",
        "And",
        "Elisha",
        "came",
        "againe",
        "to",
        "Gilgal,",
        "and",
        "there",
        "was",
        "a",
        "dearth",
        "in",
        "the",
        "land,",
        "and",
        "the",
        "sonnes",
        "of",
        "the",
        "Prophets",
        "were",
        "sitting",
        "before",
        "him:",
        "and",
        "hee",
        "said",
        "vnto",
        "his",
        "seruant,",
        "Set",
        "on",
        "the",
        "great",
        "pot,",
        "and",
        "seethe",
        "pottage",
        "for",
        "the",
        "sonnes",
        "of",
        "the",
        "Prophets."
      ],
      "info": ""
    },
    {
      "book_id": "2KI",
      "book_name": "2 Kings",
      "chapter": 4,
      "verse_start": 39,
      "verse_end": 39,
      "text": [
        "And",
        "one",
        "went",
        "out",
        "into",
        "the",
        "field",
        "to",
        "gather",
        "herbes,",
        "and",
        "found",
        "a",
        "wild",
        "vine,",
        "and",
        "gathered",
        "thereof",
        "wilde",
        "gourds",
        "his",
        "lap",
        "full,",
        "and",
        "came",
        "and",
        "shred",
        "them",
        "into",
        "the",
        "pot",
        "of",
        "pottage:",
        "for",
        "they",
        "knew",
        "them",
        "not."
      ],
      "info": ""
    },
    {
      "book_id": "2KI",
      "book_name": "2 Kings",
      "chapter": 4,
      "verse_start": 40,
      "verse_end": 40,
      "text": [
        "So",
        "they",
        "powred",
        "out",
        "for",
        "the",
        "men",
        "to",
        "eat:",
        "and",
        "it",
        "came",
        "to",
        "passe",
        "as",
        "they",
        "were",
        "eating",
        "of",
        "the",
        "pottage,",
        "that",
        "they",
        "cried",
        "out,",
        "and",
        "said,",
        "O",
        "thou",
        "man",
        "of",
        "God,",
        "there",
        "is",
        "death",
        "in",
        "the",
        "pot.",
        "And",
        "they",
        "could",
        "not",
        "eate",
        "thereof."
      ],
      "info": ""
    },
    {
      "book_id": "2KI",
      "book_name": "2 Kings",
      "chapter": 4,
      "verse_start": 41,
      "verse_end": 41,
      "text": [
        "But",
        "he",
        "said,",
        "Then",
        "bring",
        "meale.",
        "And",
        "he",
        "cast",
        "it",
        "into",
        "the",
        "pot:",
        "And",
        "he",
        "said,",
        "Powre",
        "out",
        "for",
        "the",
        "people,",
        "that",
        "they",
        "may",
        "eat.",
        "And",
        "there",
        "was",
        "no",
        "harme",
        "in",
        "the",
        "pot."
      ],
      "info": ""
    },
    {
      "book_id": "2KI",
      "book_name": "2 Kings",
      "chapter": 4,
      "verse_start": 42,
      "verse_end": 42,
      "text": [
        "¶",
        "And",
        "there",
        "came",
        "a",
        "man",
        "from",
        "Baal-Shalisha,",
        "and",
        "brought",
        "the",
        "man",
        "of",
        "God",
        "bread",
        "of",
        "the",
        "first",
        "fruits,",
        "twentie",
        "loaues",
        "of",
        "barley,",
        "and",
        "full",
        "eares",
        "of",
        "corne",
        "in",
        "the",
        "huske",
        "thereof:",
        "and",
        "he",
        "said,",
        "Giue",
        "vnto",
        "the",
        "people,",
        "that",
        "they",
        "may",
        "eate."
      ],
      "info": ""
    },
    {
      "book_id": "2KI",
      "book_name": "2 Kings",
      "chapter": 4,
      "verse_start": 43,
      "verse_end": 43,
      "text": [
        "And",
        "his",
        "seruitour",
        "saide,",
        "What",
        "should",
        "I",
        "set",
        "this",
        "before",
        "an",
        "hundred",
        "men?",
        "He",
        "said",
        "againe,",
        "Giue",
        "the",
        "people,",
        "that",
        "they",
        "may",
        "eate:",
        "for",
        "thus",
        "saith",
        "the",
        "Lord,",
        "They",
        "shall",
        "eate,",
        "and",
        "shall",
        "leaue",
        "thereof."
      ],
      "info": ""
    },
    {
      "book_id": "2KI",
      "book_name": "2 Kings",
      "chapter": 4,
      "verse_start": 44,
      "verse_end": 44,
      "text": [
        "So",
        "he",
        "set",
        "it",
        "before",
        "them,",
        "and",
        "they",
        "did",
        "eate,",
        "and",
        "left",
        "thereof,",
        "according",
        "to",
        "the",
        "word",
        "of",
        "the",
        "Lord."
      ],
      "info": ""
    }
  ]
}