[{"book_id":"PSA","book_name_alt":"Psalms","chapter":"13","verse_start":"1","verse_start_alt":"1","verse_end":"1","verse_end_alt":"1","verse_text":"How long wilt thou forget me, O LORD? for ever? how long wilt thou hide thy face from me?"},{"book_id":"PSA","book_name_alt":"Psalms","chapter":"13","verse_start":"2","verse_start_alt":"2","verse_end":"2","verse_end_alt":"2","verse_text":"How long shall I take counsel in my soul, having sorrow in my heart daily? how long shall mine enemy be exalted over me?"},{"book_id":"PSA","book_name_alt":"Psalms","chapter":"13","verse_start":"3","verse_start_alt":"3","verse_end":"3","verse_end_alt":"3","verse_text":"Consider and hear me, O LORD my God: lighten mine eyes, lest I sleep the sleep of death;"},{"book_id":"PSA","book_name_alt":"Psalms","chapter":"13","verse_start":"4","verse_start_alt":"4","verse_end":"4","verse_end_alt":"4","verse_text":"Lest mine enemy say, I have prevailed against him; and those that trouble me rejoice when I am moved."},{"book_id":"PSA","book_name_alt":"Psalms","chapter":"13","verse_start":"5","verse_start_alt":"5","verse_end":"5","verse_end_alt":"5","verse_text":"But I have trusted in thy mercy; my heart shall rejoice in thy salvation."},{"book_id":"PSA","book_name_alt":"Psalms","chapter":"13","verse_start":"6","verse_start_alt":"6","verse_end":"6","verse_end_alt":"6","verse_text":"I will sing unto the LORD, because he hath dealt bountifully with me."}]