{
  "header": "",
  "footer": "",
  "language": "Hebrew",
  "verses": [
    {
      "book_id": "DEU",
      "book_name": "Deuteronomy",
      "chapter": 5,
      "verse_start": 1,
      "verse_end": 1,
      "text": [
        "ויקרא",
        "משׁה",
        "אל",
        "כל",
        "ישׂראל",
        "ויאמר",
        "אלהם",
        "שׁמע",
        "ישׂראל",
        "את",
        "החקים",
        "ואת",
        "המשׁפטים",
        "אשׁר",
        "אנכי",
        "דבר",
        "באזניכם",
        "היום",
        "ולמדתם",
        "אתם",
        "ושׁמרתם",
        "לעשׂתם׃"
      ],
      "info": ""
    },
    {
      "book_id": "DEU",
      "book_name": "Deuteronomy",
      "chapter": 5,
      "verse_start": 2,
      "verse_end": 2,
      "text": [
        "יהוה",
        "אלהינו",
        "כרת",
        "עמנו",
        "ברית",
        "בחרב׃"
      ],
      "info": ""
    },
    {
      "book_id": "DEU",
      "book_name": "Deuteronomy",
      "chapter": 5,
      "verse_start": 3,
      "verse_end": 3,
      "text": [
        "לא",
        "את",
        "אבתינו",
        "כרת",
        "יהוה",
        "את",
        "הברית",
        "הזאת",
        "כי",
        "אתנו",
        "אנחנו",
        "אלה",
        "פה",
        "היום",
        "כלנו",
        "חיים׃"
      ],
      "info": ""
    },
    {
      "book_id": "DEU",
      "book_name": "Deuteronomy",
      "chapter": 5,
      "verse_start": 4,
      "verse_end": 4,
      "text": [
        "פנים",
        "בפנים",
        "דבר",
        "יהוה",
        "עמכם",
        "בהר",
        "מתוך",
        "האשׁ׃"
      ],
      "info": ""
    },
    {
      "book_id": "DEU",
      "book_name": "Deuteronomy",
      "chapter": 5,
      "verse_start": 5,
      "verse_end": 5,
      "text": [
        "אנכי",
        "עמד",
        "בין",
        "יהוה",
        "וביניכם",
        "בעת",
        "ההוא",
        "להגיד",
        "לכם",
        "את",
        "דבר",
        "יהוה",
        "כי",
        "יראתם",
        "מפני",
        "האשׁ",
        "ולא",
        "עליתם",
        "בהר",
        "לאמר׃"
      ],
      "info": ""
    },
    {
      "book_id": "DEU",
      "book_name": "Deuteronomy",
      "chapter": 5,
      "verse_start": 6,
      "verse_end": 6,
      "text": [
        "אנכי",
        "יהוה",
        "אלהיך",
        "אשׁר",
        "הוצאתיך",
        "מארץ",
        "מצרים",
        "מבית",
        "עבדים׃"
      ],
      "info": ""
    },
    {
      "book_id": "DEU",
      "book_name": "Deuteronomy",
      "chapter": 5,
      "verse_start": 7,
      "verse_end": 7,
      "text": [
        "לא",
        "יהיה",
        "לך",
        "אלהים",
        "אחרים",
        "על",
        "פני׃"
      ],
      "info": ""
    },
    {
      "book_id": "DEU",
      "book_name": "Deuteronomy",
      "chapter": 5,
      "verse_start": 8,
      "verse_end": 8,
      "text": [
        "לא",
        "תעשׂה",
        "לך",
        "פסל",
        "כל",
        "תמונה",
        "אשׁר",
        "בשׁמים",
        "ממעל",
        "ואשׁר",
        "בארץ",
        "מתחת",
        "ואשׁר",
        "במים",
        "מתחת",
        "לארץ׃"
      ],
      "info": ""
    },
    {
      "book_id": "DEU",
      "book_name": "Deuteronomy",
      "chapter": 5,
      "verse_start": 9,
      "verse_end": 9,
      "text": [
        "לא",
        "תשׁתחוה",
        "להם",
        "ולא",
        "תעבדם",
        "כי",
        "אנכי",
        "יהוה",
        "אלהיך",
        "אל",
        "קנא",
        "פקד",
        "עון",
        "אבות",
        "על",
        "בנים",
        "ועל",
        "שׁלשׁים",
        "ועל",
        "רבעים",
        "לשׂנאי׃"
      ],
      "info": ""
    },
    {
      "book_id": "DEU",
      "book_name": "Deuteronomy",
      "chapter": 5,
      "verse_start": 10,
      "verse_end": 10,
      "text": [
        "ועשׂה",
        "חסד",
        "לאלפים",
        "לאהבי",
        "ולשׁמרי",
        "מצותו׃"
      ],
      "info": ""
    },
    {
      "book_id": "DEU",
      "book_name": "Deuteronomy",
      "chapter": 5,
      "verse_start": 11,
      "verse_end": 11,
      "text": [
        "לא",
        "תשׂא",
        "את",
        "שׁם",
        "יהוה",
        "אלהיך",
        "לשׁוא",
        "כי",
        "לא",
        "ינקה",
        "יהוה",
        "את",
        "אשׁר",
        "ישׂא",
        "את",
        "שׁמו",
        "לשׁוא׃"
      ],
      "info": ""
    },
    {
      "book_id": "DEU",
      "book_name": "Deuteronomy",
      "chapter": 5,
      "verse_start": 12,
      "verse_end": 12,
      "text": [
        "שׁמור",
        "את",
        "יום",
        "השׁבת",
        "לקדשׁו",
        "כאשׁר",
        "צוך",
        "יהוה",
        "אלהיך׃"
      ],
      "info": ""
    },
    {
      "book_id": "DEU",
      "book_name": "Deuteronomy",
      "chapter": 5,
      "verse_start": 13,
      "verse_end": 13,
      "text": [
        "שׁשׁת",
        "ימים",
        "תעבד",
        "ועשׂית",
        "כל",
        "מלאכתך׃"
      ],
      "info": ""
    },
    {
      "book_id": "DEU",
      "book_name": "Deuteronomy",
      "chapter": 5,
      "verse_start": 14,
      "verse_end": 14,
      "text": [
        "ויום",
        "השׁביעי",
        "שׁבת",
        "ליהוה",
        "אלהיך",
        "לא",
        "תעשׂה",
        "כל",
        "מלאכה",
        "אתה",
        "ובנך",
        "ובתך",
        "ועבדך",
        "ואמתך",
        "ושׁורך",
        "וחמרך",
        "וכל",
        "בהמתך",
        "וגרך",
        "אשׁר",
        "בשׁעריך",
        "למען",
        "ינוח",
        "עבדך",
        "ואמתך",
        "כמוך׃"
      ],
      "info": ""
    },
    {
      "book_id": "DEU",
      "book_name": "Deuteronomy",
      "chapter": 5,
      "verse_start": 15,
      "verse_end": 15,
      "text": [
        "וזכרת",
        "כי",
        "עבד",
        "היית",
        "בארץ",
        "מצרים",
        "ויצאך",
        "יהוה",
        "אלהיך",
        "משׁם",
        "ביד",
        "חזקה",
        "ובזרע",
        "נטויה",
        "על",
        "כן",
        "צוך",
        "יהוה",
        "אלהיך",
        "לעשׂות",
        "את",
        "יום",
        "השׁבת׃"
      ],
      "info": ""
    },
    {
      "book_id": "DEU",
      "book_name": "Deuteronomy",
      "chapter": 5,
      "verse_start": 16,
      "verse_end": 16,
      "text": [
        "כבד",
        "את",
        "אביך",
        "ואת",
        "אמך",
        "כאשׁר",
        "צוך",
        "יהוה",
        "אלהיך",
        "למען",
        "יאריכן",
        "ימיך",
        "ולמען",
        "ייטב",
        "לך",
        "על",
        "האדמה",
        "אשׁר",
        "יהוה",
        "אלהיך",
        "נתן׃"
      ],
      "info": ""
    },
    {
      "book_id": "DEU",
      "book_name": "Deuteronomy",
      "chapter": 5,
      "verse_start": 17,
      "verse_end": 17,
      "text": [
        "לא",
        "תרצח׃"
      ],
      "info": ""
    },
    {
      "book_id": "DEU",
      "book_name": "Deuteronomy",
      "chapter": 5,
      "verse_start": 18,
      "verse_end": 18,
      "text": [
        "ולא",
        "תנאף׃"
      ],
      "info": ""
    },
    {
      "book_id": "DEU",
      "book_name": "Deuteronomy",
      "chapter": 5,
      "verse_start": 19,
      "verse_end": 19,
      "text": [
        "ולא",
        "תגנב׃"
      ],
      "info": ""
    },
    {
      "book_id": "DEU",
      "book_name": "Deuteronomy",
      "chapter": 5,
      "verse_start": 20,
      "verse_end": 20,
      "text": [
        "ולא",
        "תענה",
        "ברעך",
        "עד",
        "שׁוא׃"
      ],
      "info": ""
    },
    {
      "book_id": "DEU",
      "book_name": "Deuteronomy",
      "chapter": 5,
      "verse_start": 21,
      "verse_end": 21,
      "text": [
        "ולא",
        "תחמד",
        "אשׁת",
        "רעך",
        "ולא",
        "תתאוה",
        "בית",
        "רעך",
        "שׂדהו",
        "ועבדו",
        "ואמתו",
        "שׁורו",
        "וחמרו",
        "וכל",
        "אשׁר",
        "לרעך׃"
      ],
      "info": ""
    },
    {
      "book_id": "DEU",
      "book_name": "Deuteronomy",
      "chapter": 5,
      "verse_start": 22,
      "verse_end": 22,
      "text": [
        "את",
        "הדברים",
        "האלה",
        "דבר",
        "יהוה",
        "אל",
        "כל",
        "קהלכם",
        "בהר",
        "מתוך",
        "האשׁ",
        "הענן",
        "והערפל",
        "קול",
        "גדול",
        "ולא",
        "יסף",
        "ויכתבם",
        "על",
        "שׁני",
        "לחת",
        "אבנים",
        "ויתנם",
        "אלי׃"
      ],
      "info": ""
    },
    {
      "book_id": "DEU",
      "book_name": "Deuteronomy",
      "chapter": 5,
      "verse_start": 23,
      "verse_end": 23,
      "text": [
        "ויהי",
        "כשׁמעכם",
        "את",
        "הקול",
        "מתוך",
        "החשׁך",
        "וההר",
        "בער",
        "באשׁ",
        "ותקרבון",
        "אלי",
        "כל",
        "ראשׁי",
        "שׁבטיכם",
        "וזקניכם׃"
      ],
      "info": ""
    },
    {
      "book_id": "DEU",
      "book_name": "Deuteronomy",
      "chapter": 5,
      "verse_start": 24,
      "verse_end": 24,
      "text": [
        "ותאמרו",
        "הן",
        "הראנו",
        "יהוה",
        "אלהינו",
        "את",
        "כבדו",
        "ואת",
        "גדלו",
        "ואת",
        "קלו",
        "שׁמענו",
        "מתוך",
        "האשׁ",
        "היום",
        "הזה",
        "ראינו",
        "כי",
        "ידבר",
        "אלהים",
        "את",
        "האדם",
        "וחי׃"
      ],
      "info": ""
    },
    {
      "book_id": "DEU",
      "book_name": "Deuteronomy",
      "chapter": 5,
      "verse_start": 25,
      "verse_end": 25,
      "text": [
        "ועתה",
        "למה",
        "נמות",
        "כי",
        "תאכלנו",
        "האשׁ",
        "הגדלה",
        "הזאת",
        "אם",
        "יספים",
        "אנחנו",
        "לשׁמע",
        "את",
        "קול",
        "יהוה",
        "אלהינו",
        "עוד",
        "ומתנו׃"
      ],
      "info": ""
    },
    {
      "book_id": "DEU",
      "book_name": "Deuteronomy",
      "chapter": 5,
      "verse_start": 26,
      "verse_end": 26,
      "text": [
        "כי",
        "מי",
        "כל",
        "בשׂר",
        "אשׁר",
        "שׁמע",
        "קול",
        "אלהים",
        "חיים",
        "מדבר",
        "מתוך",
        "האשׁ",
        "כמנו",
        "ויחי׃"
      ],
      "info": ""
    },
    {
      "book_id": "DEU",
      "book_name": "Deuteronomy",
      "chapter": 5,
      "verse_start": 27,
      "verse_end": 27,
      "text": [
        "קרב",
        "אתה",
        "ושׁמע",
        "את",
        "כל",
        "אשׁר",
        "יאמר",
        "יהוה",
        "אלהינו",
        "ואת",
        "תדבר",
        "אלינו",
        "את",
        "כל",
        "אשׁר",
        "ידבר",
        "יהוה",
        "אלהינו",
        "אליך",
        "ושׁמענו",
        "ועשׂינו׃"
      ],
      "info": ""
    },
    {
      "book_id": "DEU",
      "book_name": "Deuteronomy",
      "chapter": 5,
      "verse_start": 28,
      "verse_end": 28,
      "text": [
        "וישׁמע",
        "יהוה",
        "את",
        "קול",
        "דבריכם",
        "בדברכם",
        "אלי",
        "ויאמר",
        "יהוה",
        "אלי",
        "שׁמעתי",
        "את",
        "קול",
        "דברי",
        "העם",
        "הזה",
        "אשׁר",
        "דברו",
        "אליך",
        "היטיבו",
        "כל",
        "אשׁר",
        "דברו׃"
      ],
      "info": ""
    },
    {
      "book_id": "DEU",
      "book_name": "Deuteronomy",
      "chapter": 5,
      "verse_start": 29,
      "verse_end": 29,
      "text": [
        "מי",
        "יתן",
        "והיה",
        "לבבם",
        "זה",
        "להם",
        "ליראה",
        "אתי",
        "ולשׁמר",
        "את",
        "כל",
        "מצותי",
        "כל",
        "הימים",
        "למען",
        "ייטב",
        "להם",
        "ולבניהם",
        "לעלם׃"
      ],
      "info": ""
    },
    {
      "book_id": "DEU",
      "book_name": "Deuteronomy",
      "chapter": 5,
      "verse_start": 30,
      "verse_end": 30,
      "text": [
        "לך",
        "אמר",
        "להם",
        "שׁובו",
        "לכם",
        "לאהליכם׃"
      ],
      "info": ""
    },
    {
      "book_id": "DEU",
      "book_name": "Deuteronomy",
      "chapter": 5,
      "verse_start": 31,
      "verse_end": 31,
      "text": [
        "ואתה",
        "פה",
        "עמד",
        "עמדי",
        "ואדברה",
        "אליך",
        "את",
        "כל",
        "המצוה",
        "והחקים",
        "והמשׁפטים",
        "אשׁר",
        "תלמדם",
        "ועשׂו",
        "בארץ",
        "אשׁר",
        "אנכי",
        "נתן",
        "להם",
        "לרשׁתה׃"
      ],
      "info": ""
    },
    {
      "book_id": "DEU",
      "book_name": "Deuteronomy",
      "chapter": 5,
      "verse_start": 32,
      "verse_end": 32,
      "text": [
        "ושׁמרתם",
        "לעשׂות",
        "כאשׁר",
        "צוה",
        "יהוה",
        "אלהיכם",
        "אתכם",
        "לא",
        "תסרו",
        "ימין",
        "ושׂמאל׃"
      ],
      "info": ""
    },
    {
      "book_id": "DEU",
      "book_name": "Deuteronomy",
      "chapter": 5,
      "verse_start": 33,
      "verse_end": 33,
      "text": [
        "בכל",
        "הדרך",
        "אשׁר",
        "צוה",
        "יהוה",
        "אלהיכם",
        "אתכם",
        "תלכו",
        "למען",
        "תחיון",
        "וטוב",
        "לכם",
        "והארכתם",
        "ימים",
        "בארץ",
        "אשׁר",
        "תירשׁון׃"
      ],
      "info": ""
    }
  ]
}