{
  "header": "",
  "footer": "",
  "language": "Spanish",
  "verses": [
    {
      "book_id": "ISA",
      "book_name": "Isaías",
      "chapter": 64,
      "verse_start": 1,
      "verse_end": 1,
      "text": [
        "¡Oh",
        "si",
        "rompiese",
        "los",
        "cielos,",
        "y",
        "descendieras,",
        "y",
        "a",
        "tu",
        "presencia",
        "se",
        "escurriesen",
        "los",
        "montes,"
      ],
      "info": ""
    },
    {
      "book_id": "ISA",
      "book_name": "Isaías",
      "chapter": 64,
      "verse_start": 2,
      "verse_end": 2,
      "text": [
        "como",
        "fuego",
        "abrasador",
        "de",
        "fundiciones,",
        "fuego",
        "que",
        "hace",
        "hervir",
        "las",
        "aguas,",
        "para",
        "que",
        "hicieras",
        "notorio",
        "tu",
        "nombre",
        "a",
        "tus",
        "enemigos,",
        "y",
        "las",
        "naciones",
        "temblasen",
        "a",
        "tu",
        "presencia!"
      ],
      "info": ""
    },
    {
      "book_id": "ISA",
      "book_name": "Isaías",
      "chapter": 64,
      "verse_start": 3,
      "verse_end": 3,
      "text": [
        "Cuando",
        "hiciste",
        "cosas",
        "terribles,",
        "cuales",
        "nunca",
        "esperábamos,",
        "y",
        "descendiste,",
        "se",
        "deslizaron",
        "los",
        "montes",
        "ante",
        "tu",
        "presencia."
      ],
      "info": ""
    },
    {
      "book_id": "ISA",
      "book_name": "Isaías",
      "chapter": 64,
      "verse_start": 4,
      "verse_end": 4,
      "text": [
        "Porque",
        "desde",
        "el",
        "principio",
        "del",
        "mundo",
        "no",
        "se",
        "ha",
        "escuchado,",
        "ni",
        "oído",
        "ha",
        "percibido,",
        "ni",
        "ojo",
        "ha",
        "visto",
        "a",
        "Dios",
        "fuera",
        "de",
        "ti,",
        "que",
        "hiciese",
        "por",
        "el",
        "que",
        "en",
        "Él",
        "espera."
      ],
      "info": ""
    },
    {
      "book_id": "ISA",
      "book_name": "Isaías",
      "chapter": 64,
      "verse_start": 5,
      "verse_end": 5,
      "text": [
        "Saliste",
        "al",
        "encuentro",
        "del",
        "que",
        "con",
        "alegría",
        "hacía",
        "justicia,",
        "de",
        "<em>los</em>",
        "<em>que</em>",
        "se",
        "acordaban",
        "de",
        "ti",
        "en",
        "tus",
        "caminos",
        "(he",
        "aquí,",
        "tú",
        "te",
        "enojaste",
        "cuando",
        "pecamos),",
        "en",
        "ellos",
        "hay",
        "perpetuidad,",
        "y",
        "seremos",
        "salvos."
      ],
      "info": ""
    },
    {
      "book_id": "ISA",
      "book_name": "Isaías",
      "chapter": 64,
      "verse_start": 6,
      "verse_end": 6,
      "text": [
        "Si",
        "bien",
        "todos",
        "nosotros",
        "somos",
        "como",
        "suciedad,",
        "y",
        "todas",
        "nuestras",
        "justicias",
        "como",
        "trapo",
        "de",
        "inmundicia;",
        "y",
        "caímos",
        "todos",
        "nosotros",
        "como",
        "la",
        "hoja,",
        "y",
        "nuestras",
        "maldades",
        "nos",
        "llevaron",
        "como",
        "viento."
      ],
      "info": ""
    },
    {
      "book_id": "ISA",
      "book_name": "Isaías",
      "chapter": 64,
      "verse_start": 7,
      "verse_end": 7,
      "text": [
        "Y",
        "nadie",
        "<em>hay</em>",
        "que",
        "invoque",
        "tu",
        "nombre,",
        "que",
        "se",
        "despierte",
        "para",
        "asirse",
        "de",
        "ti;",
        "por",
        "lo",
        "cual",
        "escondiste",
        "de",
        "nosotros",
        "tu",
        "rostro,",
        "y",
        "nos",
        "dejaste",
        "marchitar",
        "en",
        "poder",
        "de",
        "nuestras",
        "maldades."
      ],
      "info": ""
    },
    {
      "book_id": "ISA",
      "book_name": "Isaías",
      "chapter": 64,
      "verse_start": 8,
      "verse_end": 8,
      "text": [
        "Ahora",
        "pues,",
        "Jehová,",
        "tú",
        "<em>eres</em>",
        "nuestro",
        "Padre;",
        "nosotros",
        "barro,",
        "y",
        "tú",
        "el",
        "que",
        "nos",
        "formaste;",
        "así",
        "que",
        "obra",
        "de",
        "tus",
        "manos",
        "<em>somos</em>",
        "todos",
        "nosotros."
      ],
      "info": ""
    },
    {
      "book_id": "ISA",
      "book_name": "Isaías",
      "chapter": 64,
      "verse_start": 9,
      "verse_end": 9,
      "text": [
        "No",
        "te",
        "enojes",
        "sobremanera,",
        "oh",
        "Jehová,",
        "ni",
        "tengas",
        "perpetua",
        "memoria",
        "de",
        "la",
        "iniquidad;",
        "he",
        "aquí",
        "mira",
        "ahora,",
        "pueblo",
        "tuyo",
        "<em>somos</em>",
        "todos",
        "nosotros."
      ],
      "info": ""
    },
    {
      "book_id": "ISA",
      "book_name": "Isaías",
      "chapter": 64,
      "verse_start": 10,
      "verse_end": 10,
      "text": [
        "Tus",
        "santas",
        "ciudades",
        "están",
        "desiertas,",
        "Sión",
        "es",
        "un",
        "desierto,",
        "Jerusalén",
        "una",
        "soledad."
      ],
      "info": ""
    },
    {
      "book_id": "ISA",
      "book_name": "Isaías",
      "chapter": 64,
      "verse_start": 11,
      "verse_end": 11,
      "text": [
        "La",
        "casa",
        "de",
        "nuestro",
        "santuario",
        "y",
        "de",
        "nuestra",
        "gloria,",
        "en",
        "la",
        "cual",
        "te",
        "alabaron",
        "nuestros",
        "padres,",
        "fue",
        "consumida",
        "por",
        "el",
        "fuego;",
        "y",
        "todas",
        "nuestras",
        "cosas",
        "preciosas",
        "han",
        "sido",
        "destruidas."
      ],
      "info": ""
    },
    {
      "book_id": "ISA",
      "book_name": "Isaías",
      "chapter": 64,
      "verse_start": 12,
      "verse_end": 12,
      "text": [
        "¿Te",
        "estarás",
        "quieto,",
        "oh",
        "Jehová,",
        "sobre",
        "estas",
        "cosas?",
        "¿Callarás,",
        "y",
        "nos",
        "afligirás",
        "sobremanera?"
      ],
      "info": ""
    }
  ]
}